dongtai_sdk/DongTai.py
dongtai_sdk/DongTaiApi.py
dongtai_sdk/__init__.py
dongtai_sdk/base/BaseObejct.py
dongtai_sdk/base/DongTaiAgent.py
dongtai_sdk/base/DongTaiProject.py
dongtai_sdk/base/DongTaiSca.py
dongtai_sdk/base/DongTaiVuln.py
dongtai_sdk/base/__init__.py
dongtai_sdk-0.0.19.dist-info/LICENSE
dongtai_sdk-0.0.19.dist-info/METADATA
dongtai_sdk-0.0.19.dist-info/WHEEL
dongtai_sdk-0.0.19.dist-info/top_level.txt
dongtai_sdk-0.0.19.dist-info/zip-safe
dongtai_sdk-0.0.19.dist-info/RECORD
