Metadata-Version: 2.1
Name: dongtai_sdk
Version: 0.0.19
Summary: DongTai SDK
Home-page: https://github.com/HXSecurity/DongTai-SDK-Python
Author: spensercai
Author-email: spensercai@gmail.com
License: MIT
Platform: UNKNOWN
License-File: LICENSE
